verification_digit_pty/__init__.py
verification_digit_pty/adapters/__init__.py
verification_digit_pty/adapters/ruc/__init__.py
verification_digit_pty/adapters/ruc/natural.py
verification_digit_pty/calculators/__init__.py
verification_digit_pty/calculators/natural.py
verification_digit_pty/cli.py
verification_digit_pty/clients.py
verification_digit_pty/enums.py
verification_digit_pty/exceptions.py
verification_digit_pty/handlers.py
verification_digit_pty/plugins.py
verification_digit_pty/schemas.py
verification_digit_pty/verification_digit_pty.py
verification_digit_pty-0.2.3.dist-info/LICENSE
verification_digit_pty-0.2.3.dist-info/METADATA
verification_digit_pty-0.2.3.dist-info/WHEEL
verification_digit_pty-0.2.3.dist-info/entry_points.txt
verification_digit_pty-0.2.3.dist-info/RECORD
